{"details": {"description": {"columns": ["name", "title", "value", "type", "sort_order", "is_hidden", "precision"], "data": [["SECID", "Код ценной бумаги", "RU000A10ADT2", "string", 1, 0, null], ["ISSUENAME", "Наименование ценной бумаги", "облигации бездокументарные неконвертируемые с залоговым обеспечением денежными требованиями процентные серии 02", "string", 2, 0, null], ["NAME", "Полное наименование", "СФО Оптимум Финанс 02", "string", 3, 0, null], ["SHORTNAME", "Краткое наименование", "СФООптФин2", "string", 4, 0, null], ["REGNUMBER", "Номер государственной регистрации", "4-02-00760-R", "string", 5, 0, null], ["ISIN", "ISIN код", "RU000A10ADT2", "string", 6, 0, null], ["ISSUEDATE", "Дата начала торгов", "2024-12-20", "date", 7, 0, null], ["MATDATE", "Дата погашения", "2030-11-15", "date", 8, 0, null], ["INITIALFACEVALUE", "Первоначальная номинальная стоимость", "1000", "number", 10, 0, 2], ["FACEUNIT", "Валюта номинала", "SUR", "string", 11, 0, null], ["LATNAME", "Английское наименование", "SFO Optimum Finance 02", "string", 12, 1, null], ["STARTDATEMOEX", "Дата начала торгов на Московской Бирже", "2025-08-06", "date", 13, 0, null], ["HASPROSPECTUS", "Наличие проспекта", "0", "boolean", 14, 1, 0], ["DECISIONDATE", "Дата принятия решения организатором торговли о включении ценной бумаги в Список", "2025-07-29", "date", 15, 1, null], ["ISCONCESSIONAGREEMENT", "Облигации размещены с целью финансирования соглашений о партнерстве", "0", "boolean", 16, 1, 0], ["HASDEFAULT", "Допущен дефолт", "0", "boolean", 17, 1, 0], ["HASTECHNICALDEFAULT", "Допущен технический дефолт", "0", "boolean", 18, 1, 0], ["EMITENTMISMATCHCUR", "Эмитент не соответствует требованию на текущий Список", "0", "number", 21, 1, 0], ["LISTLEVEL", "Уровень листинга", "3", "number", 23, 0, 0], ["DAYSTOREDEMPTION", "Дней до погашения", "1729", "number", 25, 0, 0], ["ISSUESIZE", "Объем выпуска", "541521453", "number", 26, 0, 0], ["FACEVALUE", "Номинальная стоимость", "469.45", "number", 27, 0, 2], ["ISQUALIFIEDINVESTORS", "Бумаги для квалифицированных инвесторов", "1", "boolean", 28, 0, 0], ["QUALINVESTORGROUP", "Категория квалифицированного инвестора", "Все", "string", 29, 0, null], ["COUPONFREQUENCY", "Периодичность выплаты купона в год", "12", "number", 30, 0, 0], ["COUPONDATE", "Дата выплаты купона", "2026-03-15", "date", 31, 0, null], ["COUPONPERCENT", "Ставка купона, %", "18.5", "number", 32, 0, 2], ["COUPONVALUE", "Сумма купона, в валюте номинала", "6.66", "number", 33, 0, 2], ["EVENINGSESSION", "Допуск к вечерней дополнительной торговой сессии", "1", "boolean", 37, 0, 0], ["REGISTRY_DATE", "Дата государственной регистрации ценной бумаги", "2024-11-14", "date", 41, 0, null], ["BOND_TYPE", "Вид облигации", "Амортизируемые облигации", "string", 42, 1, null], ["BOND_SUBTYPE", "Подвид облигации", "До погашения", "string", 43, 1, null], ["TYPENAME", "Вид/категория ценной бумаги", "Корпоративная облигация", "string", 9000, 0, null], ["GROUP", "Код типа инструмента", "stock_bonds", "string", 9001, 1, null], ["TYPE", "Тип бумаги", "corporate_bond", "string", 10000, 1, null], ["GROUPNAME", "Типа инструмента", "Облигации", "string", 10011, 1, null], ["EMITTER_ID", "Код эмитента", "15187", "number", 11000, 1, null]]}, "boards": {"columns": ["secid", "boardid", "title", "board_group_id", "market_id", "market", "engine_id", "engine", "is_traded", "decimals", "history_from", "history_till", "listed_from", "listed_till", "is_primary", "currencyid", "unit"], "data": [["RU000A10ADT2", "TQCB", "Т+: Облигации - безадрес.", 58, 2, "bonds", 1, "stock", 1, 2, "2025-08-06", "2026-02-19", "2025-08-06", "2026-02-20", 1, "RUB", "%"], ["RU000A10ADT2", "LIQB", "Продажа обеспечения бирж.рынок - безадрес.", 120, 36, "mamc", 1, "stock", 1, 2, null, null, "2025-08-06", "2026-02-20", 0, null, "%"], ["RU000A10ADT2", "RPEY", "РЕПО в ин.валюте (CNY) - адрес.", 2, 3, "repo", 1, "stock", 1, 6, null, null, "2025-08-06", "2026-02-20", 0, "CNY", "%"], ["RU000A10ADT2", "EQRP", "РЕПО с ЦК 1 день - безадрес.", 50, 27, "ccp", 1, "stock", 1, 4, null, null, "2025-08-06", "2026-02-20", 0, "RUB", "%"], ["RU000A10ADT2", "EQRY", "РЕПО с ЦК 1 день (CNY) - безадрес.", 152, 27, "ccp", 1, "stock", 1, 4, null, null, "2025-08-06", "2026-02-20", 0, "CNY", "%"], ["RU000A10ADT2", "EQWP", "РЕПО с ЦК 7 дн. - безадрес.", 76, 27, "ccp", 1, "stock", 1, 4, null, null, "2025-08-06", "2026-02-20", 0, "RUB", "%"], ["RU000A10ADT2", "EQWY", "РЕПО с ЦК 7 дней (CNY) - безадрес.", 1116, 27, "ccp", 1, "stock", 1, 4, null, null, "2025-08-06", "2026-02-20", 0, "CNY", "%"], ["RU000A10ADT2", "LIQR", "РЕПО с ЦК: Урегулирование - безадрес.", 148, 27, "ccp", 1, "stock", 1, 4, null, null, "2025-08-06", "2026-02-20", 0, "RUB", "%"], ["RU000A10ADT2", "PSRP", "РЕПО с ЦК - адрес.", 65, 27, "ccp", 1, "stock", 1, 4, null, null, "2025-08-06", "2026-02-20", 0, "RUB", "%"], ["RU000A10ADT2", "PSRY", "РЕПО с ЦК (CNY) - адрес.", 153, 27, "ccp", 1, "stock", 1, 4, null, null, "2025-08-06", "2026-02-20", 0, "CNY", "%"], ["RU000A10ADT2", "PSRK", "РЕПО с ЦК (KZT) - адрес.", 1422, 27, "ccp", 1, "stock", 1, 4, null, null, "2025-08-06", "2026-02-20", 0, "KZT", "%"], ["RU000A10ADT2", "PSRB", "РЕПО с ЦК (BYN) - адрес.", 1424, 27, "ccp", 1, "stock", 1, 4, null, null, "2025-08-06", "2026-02-20", 0, "BYN", "%"], ["RU000A10ADT2", "PSOB", "РПС: Облигации - адрес.", 284, 4, "ndm", 1, "stock", 1, 2, null, null, "2025-08-06", "2026-02-20", 0, "RUB", "%"], ["RU000A10ADT2", "PTOB", "РПС с ЦК: Облигации - адрес.", 282, 4, "ndm", 1, "stock", 1, 2, null, null, "2025-08-06", "2026-02-20", 0, "RUB", "%"], ["RU000A10ADT2", "OCBR", "OTC: Облигации с ЦК - двусторонние", 1017, 1014, "ndm", 1012, "otc", 1, 4, null, null, "2025-08-06", "2026-02-20", 0, "RUB", "%"], ["RU000A10ADT2", "OCBY", "OTC: Облигации с ЦК (CNY) - двусторонние", 1204, 1014, "ndm", 1012, "otc", 1, 4, null, null, "2025-08-06", "2026-02-20", 0, "CNY", "%"], ["RU000A10ADT2", "OCAR", "OTC: Облигации с ЦК адрес. - двусторонние", 1263, 1014, "ndm", 1012, "otc", 1, 4, null, null, "2025-08-06", "2026-02-20", 0, "RUB", "%"], ["RU000A10ADT2", "OCAY", "OTC: Облигации с ЦК адрес. (CNY) - двусторонние", 1265, 1014, "ndm", 1012, "otc", 1, 4, null, null, "2025-08-06", "2026-02-20", 0, "CNY", "%"], ["RU000A10ADT2", "RPMO", "РЕПО-М - адрес.", 201, 3, "repo", 1, "stock", 1, 4, null, null, "2025-08-06", "2026-02-20", 0, "RUB", "%"], ["RU000A10ADT2", "RPEK", "РЕПО-М в ин. валюте: (KZT) - адрес.", 1426, 3, "repo", 1, "stock", 1, 6, null, null, "2025-08-06", "2026-02-20", 0, "KZT", "%"], ["RU000A10ADT2", "RPEB", "РЕПО-М в ин. валюте: (BYN) - адрес.", 1428, 3, "repo", 1, "stock", 1, 6, null, null, "2025-08-06", "2026-02-20", 0, "BYN", "%"], ["RU000A10ADT2", "CIQR", "Урегулирование РЕПО с ЦК Нерезиденты - безадрес.", 1080, 1019, "nonresccp", 1, "stock", 1, 4, null, null, "2025-08-06", "2026-02-20", 0, "RUB", "%"], ["RU000A10ADT2", "CIQB", "Урегулирование с ЦК Нерезиденты - безадрес.", 1082, 36, "mamc", 1, "stock", 1, 2, null, null, "2025-08-06", "2026-02-20", 0, null, "%"], ["RU000A10ADT2", "CTOB", "РПС с ЦК Нерезиденты: Облигации - адрес.", 1062, 1015, "nonresndm", 1, "stock", 1, 2, null, null, "2025-08-06", "2026-02-20", 0, "RUB", "%"], ["RU000A10ADT2", "CPMO", "РЕПО-M Нерезиденты - адрес.", 1071, 1017, "nonresrepo", 1, "stock", 1, 4, null, null, "2025-08-06", "2026-02-20", 0, "RUB", "%"], ["RU000A10ADT2", "CPEY", "РЕПО-M Нерезиденты (CNY) - адрес.", 1077, 1017, "nonresrepo", 1, "stock", 1, 6, null, null, "2025-08-06", "2026-02-20", 0, "CNY", "%"], ["RU000A10ADT2", "QBND", "Квоты", 1280, 1279, "bonds", 1282, "quotes", 1, 4, null, null, "2025-08-06", "2026-02-20", 0, null, "%"]]}}, "bondization": {"amortizations": {"columns": ["isin", "name", "issuevalue", "amortdate", "facevalue", "initialfacevalue", "faceunit", "valueprc", "value", "value_rub", "data_source", "secid", "primary_boardid"], "data": [["RU000A10ADT2", "СФО Оптимум Финанс 02", 541521453000, "2025-02-15", 469.45, 1000, "RUB", 4.96, 49.62, 49.62, "amortization", "RU000A10ADT2", "TQCB"], ["RU000A10ADT2", "СФО Оптимум Финанс 02", 541521453000, "2025-03-15", 469.45, 1000, "RUB", 4.47, 44.74, 44.74, "amortization", "RU000A10ADT2", "TQCB"], ["RU000A10ADT2", "СФО Оптимум Финанс 02", 541521453000, "2025-04-15", 469.45, 1000, "RUB", 3.98, 39.78, 39.78, "amortization", "RU000A10ADT2", "TQCB"], ["RU000A10ADT2", "СФО Оптимум Финанс 02", 541521453000, "2025-05-15", 469.45, 1000, "RUB", 4, 39.97, 39.97, "amortization", "RU000A10ADT2", "TQCB"], ["RU000A10ADT2", "СФО Оптимум Финанс 02", 541521453000, "2025-06-15", 469.45, 1000, "RUB", 4.08, 40.82, 40.82, "amortization", "RU000A10ADT2", "TQCB"], ["RU000A10ADT2", "СФО Оптимум Финанс 02", 541521453000, "2025-07-15", 469.45, 1000, "RUB", 3.55, 35.5, 35.5, "amortization", "RU000A10ADT2", "TQCB"], ["RU000A10ADT2", "СФО Оптимум Финанс 02", 541521453000, "2025-08-15", 469.45, 1000, "RUB", 4.72, 47.2, 47.2, "amortization", "RU000A10ADT2", "TQCB"], ["RU000A10ADT2", "СФО Оптимум Финанс 02", 541521453000, "2025-09-15", 469.45, 1000, "RUB", 4.11, 41.07, 41.07, "amortization", "RU000A10ADT2", "TQCB"], ["RU000A10ADT2", "СФО Оптимум Финанс 02", 541521453000, "2025-10-15", 469.45, 1000, "RUB", 4.1, 41.02, 41.02, "amortization", "RU000A10ADT2", "TQCB"], ["RU000A10ADT2", "СФО Оптимум Финанс 02", 541521453000, "2025-11-15", 469.45, 1000, "RUB", 3.88, 38.8, 38.8, "amortization", "RU000A10ADT2", "TQCB"], ["RU000A10ADT2", "СФО Оптимум Финанс 02", 541521453000, "2025-12-15", 469.45, 1000, "RUB", 3.7, 36.95, 36.95, "amortization", "RU000A10ADT2", "TQCB"], ["RU000A10ADT2", "СФО Оптимум Финанс 02", 541521453000, "2026-01-15", 469.45, 1000, "RUB", 3.32, 33.25, 33.25, "amortization", "RU000A10ADT2", "TQCB"], ["RU000A10ADT2", "СФО Оптимум Финанс 02", 541521453000, "2026-02-15", 469.45, 1000, "RUB", 4.18, 41.83, 41.83, "amortization", "RU000A10ADT2", "TQCB"], ["RU000A10ADT2", "СФО Оптимум Финанс 02", 541521453000, "2026-03-15", 469.45, 1000, "RUB", 3.22, 32.18, 32.18, "amortization", "RU000A10ADT2", "TQCB"], ["RU000A10ADT2", "СФО Оптимум Финанс 02", 541521453000, "2026-04-15", 469.45, 1000, "RUB", 3.1, 30.98, 30.98, "amortization", "RU000A10ADT2", "TQCB"], ["RU000A10ADT2", "СФО Оптимум Финанс 02", 541521453000, "2026-05-15", 469.45, 1000, "RUB", 2.98, 29.81, 29.81, "amortization", "RU000A10ADT2", "TQCB"], ["RU000A10ADT2", "СФО Оптимум Финанс 02", 541521453000, "2026-06-15", 469.45, 1000, "RUB", 2.87, 28.67, 28.67, "amortization", "RU000A10ADT2", "TQCB"], ["RU000A10ADT2", "СФО Оптимум Финанс 02", 541521453000, "2026-07-15", 469.45, 1000, "RUB", 2.76, 27.55, 27.55, "amortization", "RU000A10ADT2", "TQCB"], ["RU000A10ADT2", "СФО Оптимум Финанс 02", 541521453000, "2026-08-15", 469.45, 1000, "RUB", 2.65, 26.47, 26.47, "amortization", "RU000A10ADT2", "TQCB"], ["RU000A10ADT2", "СФО Оптимум Финанс 02", 541521453000, "2026-09-15", 469.45, 1000, "RUB", 2.54, 25.42, 25.42, "amortization", "RU000A10ADT2", "TQCB"]]}, "coupons": {"columns": ["isin", "name", "issuevalue", "coupondate", "recorddate", "startdate", "initialfacevalue", "facevalue", "faceunit", "value", "valueprc", "value_rub", "secid", "primary_boardid"], "data": [["RU000A10ADT2", "СФО Оптимум Финанс 02", 541521453000, "2025-02-15", null, "2024-12-20", 1000, 469.45, "RUB", 28.89, 18.5, 28.89, "RU000A10ADT2", "TQCB"], ["RU000A10ADT2", "СФО Оптимум Финанс 02", 541521453000, "2025-03-15", null, "2025-02-15", 1000, 469.45, "RUB", 13.49, 18.5, 13.49, "RU000A10ADT2", "TQCB"], ["RU000A10ADT2", "СФО Оптимум Финанс 02", 541521453000, "2025-04-15", null, "2025-03-15", 1000, 469.45, "RUB", 14.23, 18.5, 14.23, "RU000A10ADT2", "TQCB"], ["RU000A10ADT2", "СФО Оптимум Финанс 02", 541521453000, "2025-05-15", null, "2025-04-15", 1000, 469.45, "RUB", 13.17, 18.5, 13.17, "RU000A10ADT2", "TQCB"], ["RU000A10ADT2", "СФО Оптимум Финанс 02", 541521453000, "2025-06-15", null, "2025-05-15", 1000, 469.45, "RUB", 12.98, 18.5, 12.98, "RU000A10ADT2", "TQCB"], ["RU000A10ADT2", "СФО Оптимум Финанс 02", 541521453000, "2025-07-15", null, "2025-06-15", 1000, 469.45, "RUB", 11.94, 18.5, 11.94, "RU000A10ADT2", "TQCB"], ["RU000A10ADT2", "СФО Оптимум Финанс 02", 541521453000, "2025-08-15", "2025-08-14", "2025-07-15", 1000, 469.45, "RUB", 11.78, 18.5, 11.78, "RU000A10ADT2", "TQCB"], ["RU000A10ADT2", "СФО Оптимум Финанс 02", 541521453000, "2025-09-15", "2025-09-12", "2025-08-15", 1000, 469.45, "RUB", 11.04, 18.5, 11.04, "RU000A10ADT2", "TQCB"], ["RU000A10ADT2", "СФО Оптимум Финанс 02", 541521453000, "2025-10-15", "2025-10-14", "2025-09-15", 1000, 469.45, "RUB", 10.06, 18.5, 10.06, "RU000A10ADT2", "TQCB"], ["RU000A10ADT2", "СФО Оптимум Финанс 02", 541521453000, "2025-11-15", "2025-11-14", "2025-10-15", 1000, 469.45, "RUB", 9.75, 18.5, 9.75, "RU000A10ADT2", "TQCB"], ["RU000A10ADT2", "СФО Оптимум Финанс 02", 541521453000, "2025-12-15", "2025-12-12", "2025-11-15", 1000, 469.45, "RUB", 8.84, 18.5, 8.84, "RU000A10ADT2", "TQCB"], ["RU000A10ADT2", "СФО Оптимум Финанс 02", 541521453000, "2026-01-15", "2026-01-14", "2025-12-15", 1000, 469.45, "RUB", 8.56, 18.5, 8.56, "RU000A10ADT2", "TQCB"], ["RU000A10ADT2", "СФО Оптимум Финанс 02", 541521453000, "2026-02-15", "2026-02-13", "2026-01-15", 1000, 469.45, "RUB", 8.03, 18.5, 8.03, "RU000A10ADT2", "TQCB"], ["RU000A10ADT2", "СФО Оптимум Финанс 02", 541521453000, "2026-03-15", "2026-03-13", "2026-02-15", 1000, 469.45, "RUB", 6.66, 18.5, 6.66, "RU000A10ADT2", "TQCB"], ["RU000A10ADT2", "СФО Оптимум Финанс 02", 541521453000, "2026-04-15", "2026-04-14", "2026-03-15", 1000, 469.45, "RUB", 6.87, 18.5, 6.87, "RU000A10ADT2", "TQCB"], ["RU000A10ADT2", "СФО Оптимум Финанс 02", 541521453000, "2026-05-15", "2026-05-14", "2026-04-15", 1000, 469.45, "RUB", 6.18, 18.5, 6.18, "RU000A10ADT2", "TQCB"], ["RU000A10ADT2", "СФО Оптимум Финанс 02", 541521453000, "2026-06-15", "2026-06-11", "2026-05-15", 1000, 469.45, "RUB", 5.92, 18.5, 5.92, "RU000A10ADT2", "TQCB"], ["RU000A10ADT2", "СФО Оптимум Финанс 02", 541521453000, "2026-07-15", "2026-07-14", "2026-06-15", 1000, 469.45, "RUB", 5.29, 18.5, 5.29, "RU000A10ADT2", "TQCB"], ["RU000A10ADT2", "СФО Оптимум Финанс 02", 541521453000, "2026-08-15", "2026-08-14", "2026-07-15", 1000, 469.45, "RUB", 5.03, 18.5, 5.03, "RU000A10ADT2", "TQCB"], ["RU000A10ADT2", "СФО Оптимум Финанс 02", 541521453000, "2026-09-15", "2026-09-14", "2026-08-15", 1000, 469.45, "RUB", 4.62, 18.5, 4.62, "RU000A10ADT2", "TQCB"]]}, "offers": {"columns": ["isin", "name", "issuevalue", "offerdate", "offerdatestart", "offerdateend", "facevalue", "faceunit", "price", "value", "agent", "offertype", "secid", "primary_boardid"], "data": []}}}