{
  "description": {
    "metadata": {
      "name": {
        "type": "string",
        "bytes": 189,
        "max_size": 0
      },
      "title": {
        "type": "string",
        "bytes": 765,
        "max_size": 0
      },
      "value": {
        "type": "string",
        "bytes": 6144,
        "max_size": 0
      },
      "type": {
        "type": "string",
        "bytes": 21,
        "max_size": 0
      },
      "sort_order": {
        "type": "int64"
      },
      "is_hidden": {
        "type": "int64"
      },
      "precision": {
        "type": "int64"
      }
    },
    "columns": [
      "name",
      "title",
      "value",
      "type",
      "sort_order",
      "is_hidden",
      "precision"
    ],
    "data": [
      [
        "SECID",
        "Security code",
        "RU000A0ZZ885",
        "string",
        1,
        0,
        null
      ],
      [
        "ISSUENAME",
        "Security name",
        "Облигации процентные неконвертируемые документарные на предъявителя с обязательным централизованным хранением серии БО-09",
        "string",
        2,
        0,
        null
      ],
      [
        "NAME",
        "Full name",
        "KAMAZ PTC BO-09",
        "string",
        3,
        0,
        null
      ],
      [
        "SHORTNAME",
        "Short name",
        "KAMAZ PTC BO-09",
        "string",
        4,
        0,
        null
      ],
      [
        "REGNUMBER",
        "State registration  number",
        "4-09-55010-D",
        "string",
        5,
        0,
        null
      ],
      [
        "ISIN",
        "ISIN Code",
        "RU000A0ZZ885",
        "string",
        6,
        0,
        null
      ],
      [
        "ISSUEDATE",
        "Date of listing",
        "2018-05-29",
        "date",
        7,
        0,
        null
      ],
      [
        "MATDATE",
        "Maturity date",
        "2033-05-10",
        "date",
        8,
        0,
        null
      ],
      [
        "INITIALFACEVALUE",
        "Initial face value",
        "1000",
        "number",
        10,
        0,
        2
      ],
      [
        "FACEUNIT",
        "Face value currency",
        "SUR",
        "string",
        11,
        0,
        null
      ],
      [
        "LATNAME",
        "Full name in English",
        "KAMAZ PTC BO-09",
        "string",
        12,
        1,
        null
      ],
      [
        "STARTDATEMOEX",
        "Trading start date on Moscow Exchange",
        "2018-05-29",
        "date",
        13,
        0,
        null
      ],
      [
        "HASPROSPECTUS",
        "Has prospectus",
        "1",
        "boolean",
        14,
        1,
        0
      ],
      [
        "DECISIONDATE",
        "Date of listing",
        "2016-12-05",
        "date",
        15,
        1,
        null
      ],
      [
        "ISCONCESSIONAGREEMENT",
        "The bonds were placed to fund partnership agreements",
        "0",
        "boolean",
        16,
        1,
        0
      ],
      [
        "HASDEFAULT",
        "Defaulted",
        "0",
        "boolean",
        17,
        1,
        0
      ],
      [
        "HASTECHNICALDEFAULT",
        "Technically defaulted",
        "0",
        "boolean",
        18,
        1,
        0
      ],
      [
        "EMITENTMISMATCHCUR",
        "The Issuer is not eligible for the current List",
        "0",
        "number",
        21,
        1,
        0
      ],
      [
        "EARLYREPAYMENT",
        "Option for early redemption",
        "0",
        "boolean",
        22,
        1,
        0
      ],
      [
        "LISTLEVEL",
        "List level",
        "2",
        "number",
        23,
        0,
        0
      ],
      [
        "DAYSTOREDEMPTION",
        "Days to redemption",
        "2649",
        "number",
        25,
        0,
        0
      ],
      [
        "ISSUESIZE",
        "Issue Size",
        "3000000",
        "number",
        26,
        0,
        0
      ],
      [
        "FACEVALUE",
        "Face value",
        "1000",
        "number",
        27,
        0,
        2
      ],
      [
        "ISQUALIFIEDINVESTORS",
        "Qualified investors",
        "0",
        "boolean",
        28,
        0,
        0
      ],
      [
        "COUPONFREQUENCY",
        "Coupon payment interval in year",
        "2",
        "number",
        30,
        0,
        0
      ],
      [
        "COUPONDATE",
        "Coupon date",
        "2026-05-19",
        "date",
        31,
        0,
        null
      ],
      [
        "COUPONPERCENT",
        "Coupon rate, %",
        "15.43",
        "number",
        32,
        0,
        2
      ],
      [
        "COUPONVALUE",
        "Coupon value, in face value currency",
        "76.94",
        "number",
        33,
        0,
        2
      ],
      [
        "EVENINGSESSION",
        "Admission to the evening additional trading session",
        "1",
        "boolean",
        37,
        0,
        0
      ],
      [
        "REGISTRY_DATE",
        "Date of state registration of the security",
        "2015-06-04",
        "date",
        41,
        0,
        null
      ],
      [
        "BOND_TYPE",
        "Bond type",
        "Floater",
        "string",
        42,
        1,
        null
      ],
      [
        "BOND_SUBTYPE",
        "Bond sub-type",
        "Till maturity",
        "string",
        43,
        1,
        null
      ],
      [
        "TYPENAME",
        "Security type",
        "Bond",
        "string",
        9000,
        0,
        null
      ],
      [
        "GROUP",
        "Instrument type code",
        "stock_bonds",
        "string",
        9001,
        1,
        null
      ],
      [
        "TYPE",
        "Security type",
        "corporate_bond",
        "string",
        10000,
        1,
        null
      ],
      [
        "GROUPNAME",
        "Instrument type",
        "Bonds",
        "string",
        10011,
        1,
        null
      ],
      [
        "EMITTER_ID",
        "Emitter code",
        "855",
        "number",
        11000,
        1,
        null
      ]
    ]
  },
  "boards": {
    "metadata": {
      "secid": {
        "type": "string",
        "bytes": 51,
        "max_size": 0
      },
      "boardid": {
        "type": "string",
        "bytes": 12,
        "max_size": 0
      },
      "title": {
        "type": "string",
        "bytes": 381,
        "max_size": 0
      },
      "board_group_id": {
        "type": "int32"
      },
      "market_id": {
        "type": "int32"
      },
      "market": {
        "type": "string",
        "bytes": 45,
        "max_size": 0
      },
      "engine_id": {
        "type": "int32"
      },
      "engine": {
        "type": "string",
        "bytes": 45,
        "max_size": 0
      },
      "is_traded": {
        "type": "int32"
      },
      "decimals": {
        "type": "int32"
      },
      "history_from": {
        "type": "date",
        "bytes": 10,
        "max_size": 0
      },
      "history_till": {
        "type": "date",
        "bytes": 10,
        "max_size": 0
      },
      "listed_from": {
        "type": "date",
        "bytes": 10,
        "max_size": 0
      },
      "listed_till": {
        "type": "date",
        "bytes": 10,
        "max_size": 0
      },
      "is_primary": {
        "type": "int32"
      },
      "currencyid": {
        "type": "string",
        "bytes": 9,
        "max_size": 0
      },
      "unit": {
        "type": "string",
        "bytes": 3,
        "max_size": 0
      }
    },
    "columns": [
      "secid",
      "boardid",
      "title",
      "board_group_id",
      "market_id",
      "market",
      "engine_id",
      "engine",
      "is_traded",
      "decimals",
      "history_from",
      "history_till",
      "listed_from",
      "listed_till",
      "is_primary",
      "currencyid",
      "unit"
    ],
    "data": [
      [
        "RU000A0ZZ885",
        "TQCB",
        "T+: Bonds - order-driven",
        58,
        2,
        "bonds",
        1,
        "stock",
        1,
        2,
        "2020-05-25",
        "2026-02-06",
        "2020-05-25",
        "2026-02-07",
        1,
        "RUB",
        "%"
      ],
      [
        "RU000A0ZZ885",
        "EQOB",
        "Main market: A1 bonds - order-driven",
        7,
        2,
        "bonds",
        1,
        "stock",
        0,
        2,
        "2018-05-29",
        "2020-05-22",
        "2018-05-29",
        "2020-05-22",
        0,
        "RUB",
        "%"
      ],
      [
        "RU000A0ZZ885",
        "LIQB",
        "Order-driven CCP deals - order-driven",
        120,
        36,
        "mamc",
        1,
        "stock",
        1,
        2,
        null,
        null,
        "2018-12-07",
        "2026-02-07",
        0,
        null,
        "%"
      ],
      [
        "RU000A0ZZ885",
        "RPEY",
        "REPO (CNY) - negotiated",
        2,
        3,
        "repo",
        1,
        "stock",
        1,
        6,
        null,
        null,
        "2022-09-26",
        "2026-02-07",
        0,
        "CNY",
        "%"
      ],
      [
        "RU000A0ZZ885",
        "RPEU",
        "REPO (USD) - negotiated",
        94,
        3,
        "repo",
        1,
        "stock",
        1,
        6,
        null,
        null,
        "2019-04-22",
        "2026-02-07",
        0,
        "USD",
        "%"
      ],
      [
        "RU000A0ZZ885",
        "RPUO",
        "REPO: bonds (USD) - negotiated",
        94,
        3,
        "repo",
        1,
        "stock",
        0,
        6,
        null,
        null,
        "2018-05-29",
        "2019-05-31",
        0,
        "USD",
        "%"
      ],
      [
        "RU000A0ZZ885",
        "RPEO",
        "REPO (EUR) - negotiated",
        90,
        3,
        "repo",
        1,
        "stock",
        1,
        6,
        null,
        null,
        "2019-04-22",
        "2026-02-07",
        0,
        "EUR",
        "%"
      ],
      [
        "RU000A0ZZ885",
        "EQRP",
        "REPO with CCP 1 day - order-driven",
        50,
        27,
        "ccp",
        1,
        "stock",
        1,
        4,
        "2019-12-11",
        "2023-09-19",
        "2018-12-07",
        "2026-02-07",
        0,
        "RUB",
        "%"
      ],
      [
        "RU000A0ZZ885",
        "EQRD",
        "REPO with CCP 1 day (USD) - order-driven",
        92,
        27,
        "ccp",
        1,
        "stock",
        1,
        4,
        null,
        null,
        "2018-12-07",
        "2026-02-07",
        0,
        "USD",
        "%"
      ],
      [
        "RU000A0ZZ885",
        "EQRE",
        "REPO with CCP 1 day (EUR) - order-driven",
        93,
        27,
        "ccp",
        1,
        "stock",
        1,
        4,
        null,
        null,
        "2018-12-07",
        "2026-02-07",
        0,
        "EUR",
        "%"
      ],
      [
        "RU000A0ZZ885",
        "EQRY",
        "REPO CCP 1 day (CNY) - order-driven",
        152,
        27,
        "ccp",
        1,
        "stock",
        1,
        4,
        null,
        null,
        "2019-03-07",
        "2026-02-07",
        0,
        "CNY",
        "%"
      ],
      [
        "RU000A0ZZ885",
        "EQWP",
        "REPO with CCP 7 day - order-driven",
        76,
        27,
        "ccp",
        1,
        "stock",
        1,
        4,
        null,
        null,
        "2018-12-07",
        "2026-02-07",
        0,
        "RUB",
        "%"
      ],
      [
        "RU000A0ZZ885",
        "EQWD",
        "REPO with CCP 7 day (USD) - order-driven",
        78,
        27,
        "ccp",
        1,
        "stock",
        1,
        4,
        null,
        null,
        "2018-12-07",
        "2026-02-07",
        0,
        "USD",
        "%"
      ],
      [
        "RU000A0ZZ885",
        "EQWE",
        "REPO with CCP 7 day (EUR) - order-driven",
        79,
        27,
        "ccp",
        1,
        "stock",
        1,
        4,
        null,
        null,
        "2018-12-07",
        "2026-02-07",
        0,
        "EUR",
        "%"
      ],
      [
        "RU000A0ZZ885",
        "EQWY",
        "REPO with CCP 7 day (CNY) - order-driven",
        1116,
        27,
        "ccp",
        1,
        "stock",
        1,
        4,
        null,
        null,
        "2022-09-26",
        "2026-02-07",
        0,
        "CNY",
        "%"
      ],
      [
        "RU000A0ZZ885",
        "LIQR",
        "REPO CCP Settle's Deals - order-driven",
        148,
        27,
        "ccp",
        1,
        "stock",
        1,
        4,
        null,
        null,
        "2019-03-04",
        "2026-02-07",
        0,
        "RUB",
        "%"
      ],
      [
        "RU000A0ZZ885",
        "PSRP",
        "REPO with CCP - negotiated",
        65,
        27,
        "ccp",
        1,
        "stock",
        1,
        4,
        "2019-10-02",
        "2020-04-17",
        "2018-12-07",
        "2026-02-07",
        0,
        "RUB",
        "%"
      ],
      [
        "RU000A0ZZ885",
        "PSRD",
        "REPO with CCP (USD) - negotiated",
        91,
        27,
        "ccp",
        1,
        "stock",
        1,
        4,
        null,
        null,
        "2018-12-07",
        "2026-02-07",
        0,
        "USD",
        "%"
      ],
      [
        "RU000A0ZZ885",
        "PSRE",
        "REPO with CCP (EUR) - negotiated",
        96,
        27,
        "ccp",
        1,
        "stock",
        1,
        4,
        null,
        null,
        "2018-12-07",
        "2026-02-07",
        0,
        "EUR",
        "%"
      ],
      [
        "RU000A0ZZ885",
        "PSRY",
        "REPO CCP (CNY) - negotiated",
        153,
        27,
        "ccp",
        1,
        "stock",
        1,
        4,
        null,
        null,
        "2019-03-07",
        "2026-02-07",
        0,
        "CNY",
        "%"
      ],
      [
        "RU000A0ZZ885",
        "PSRK",
        "REPO with CCP (KZT) - negotiated",
        1422,
        27,
        "ccp",
        1,
        "stock",
        1,
        4,
        null,
        null,
        "2025-06-23",
        "2026-02-07",
        0,
        "KZT",
        "%"
      ],
      [
        "RU000A0ZZ885",
        "PSRB",
        "REPO with CCP (BYN) - negotiated",
        1424,
        27,
        "ccp",
        1,
        "stock",
        1,
        4,
        null,
        null,
        "2025-06-23",
        "2026-02-07",
        0,
        "BYN",
        "%"
      ],
      [
        "RU000A0ZZ885",
        "PSOB",
        "Neg. deals: bonds - negotiated",
        284,
        4,
        "ndm",
        1,
        "stock",
        1,
        2,
        "2018-05-29",
        "2025-12-30",
        "2018-05-29",
        "2026-02-07",
        0,
        "RUB",
        "%"
      ],
      [
        "RU000A0ZZ885",
        "PSAU",
        "Primary distribution auction - negotiated",
        107,
        4,
        "ndm",
        1,
        "stock",
        0,
        2,
        "2018-05-29",
        "2018-05-29",
        "2018-05-29",
        "2018-05-29",
        0,
        "RUB",
        "%"
      ],
      [
        "RU000A0ZZ885",
        "OTCB",
        "Neg. deals: Anonymous - negotiated",
        126,
        4,
        "ndm",
        1,
        "stock",
        0,
        2,
        null,
        null,
        "2018-10-29",
        "2022-12-30",
        0,
        "RUB",
        "%"
      ],
      [
        "RU000A0ZZ885",
        "PTOB",
        "Neg. deals CCP: bonds - negotiated",
        282,
        4,
        "ndm",
        1,
        "stock",
        1,
        2,
        "2019-03-11",
        "2024-03-15",
        "2018-12-07",
        "2026-02-07",
        0,
        "RUB",
        "%"
      ],
      [
        "RU000A0ZZ885",
        "OCBR",
        "OTC: Bonds with CCP",
        1017,
        1014,
        "ndm",
        1012,
        "otc",
        1,
        4,
        null,
        null,
        "2022-04-25",
        "2026-02-06",
        0,
        "RUB",
        "%"
      ],
      [
        "RU000A0ZZ885",
        "OCBU",
        "OTC: Bonds with CCP (USD)",
        1019,
        1014,
        "ndm",
        1012,
        "otc",
        1,
        4,
        null,
        null,
        "2022-04-25",
        "2026-02-06",
        0,
        "USD",
        "%"
      ],
      [
        "RU000A0ZZ885",
        "OCBY",
        "OTC: Bonds with CCP (CNY)",
        1204,
        1014,
        "ndm",
        1012,
        "otc",
        1,
        4,
        null,
        null,
        "2022-12-05",
        "2026-02-06",
        0,
        "CNY",
        "%"
      ],
      [
        "RU000A0ZZ885",
        "OCAR",
        "OTC: Bonds with CCP ndm",
        1263,
        1014,
        "ndm",
        1012,
        "otc",
        1,
        4,
        null,
        null,
        "2023-04-10",
        "2026-02-06",
        0,
        "RUB",
        "%"
      ],
      [
        "RU000A0ZZ885",
        "OCAY",
        "OTC: Bonds with CCP ndm (CNY)",
        1265,
        1014,
        "ndm",
        1012,
        "otc",
        1,
        4,
        null,
        null,
        "2023-04-10",
        "2026-02-06",
        0,
        "CNY",
        "%"
      ],
      [
        "RU000A0ZZ885",
        "OCAU",
        "OTC: Bonds with CCP ndm (USD)",
        1267,
        1014,
        "ndm",
        1012,
        "otc",
        1,
        4,
        null,
        null,
        "2023-04-10",
        "2026-02-06",
        0,
        "USD",
        "%"
      ],
      [
        "RU000A0ZZ885",
        "RPMO",
        "REPO-M - negotiated",
        201,
        3,
        "repo",
        1,
        "stock",
        1,
        4,
        "2018-05-29",
        "2020-02-06",
        "2018-05-29",
        "2026-02-07",
        0,
        "RUB",
        "%"
      ],
      [
        "RU000A0ZZ885",
        "RPEK",
        "REPO-M (KZT) - negotiated",
        1426,
        3,
        "repo",
        1,
        "stock",
        1,
        6,
        null,
        null,
        "2025-06-23",
        "2026-02-07",
        0,
        "KZT",
        "%"
      ],
      [
        "RU000A0ZZ885",
        "RPEB",
        "REPO-M (BYN) - negotiated",
        1428,
        3,
        "repo",
        1,
        "stock",
        1,
        6,
        null,
        null,
        "2025-06-23",
        "2026-02-07",
        0,
        "BYN",
        "%"
      ],
      [
        "RU000A0ZZ885",
        "CIQR",
        "REPO CCP settle's Deals : Non-residents - order-driven",
        1080,
        1019,
        "nonresccp",
        1,
        "stock",
        1,
        4,
        null,
        null,
        "2022-06-27",
        "2026-02-07",
        0,
        "RUB",
        "%"
      ],
      [
        "RU000A0ZZ885",
        "CIQB",
        "Neg. CCP settle's Deals: Non-residents - order-driven",
        1082,
        36,
        "mamc",
        1,
        "stock",
        1,
        2,
        null,
        null,
        "2022-06-27",
        "2026-02-07",
        0,
        null,
        "%"
      ],
      [
        "RU000A0ZZ885",
        "CTOB",
        "Neg. deals CCP Non-residents: Bonds - negotiated",
        1062,
        1015,
        "nonresndm",
        1,
        "stock",
        1,
        2,
        null,
        null,
        "2022-06-27",
        "2026-02-07",
        0,
        "RUB",
        "%"
      ],
      [
        "RU000A0ZZ885",
        "CPMO",
        "REPO-M: Non-residents - negotiated",
        1071,
        1017,
        "nonresrepo",
        1,
        "stock",
        1,
        4,
        null,
        null,
        "2022-06-27",
        "2026-02-07",
        0,
        "RUB",
        "%"
      ],
      [
        "RU000A0ZZ885",
        "CPEU",
        "REPO-M: Non-residents (USD) - negotiated",
        1073,
        1017,
        "nonresrepo",
        1,
        "stock",
        1,
        6,
        null,
        null,
        "2022-06-27",
        "2026-02-07",
        0,
        "USD",
        "%"
      ],
      [
        "RU000A0ZZ885",
        "CPEO",
        "REPO-M: Non-residents (EUR) - negotiated",
        1075,
        1017,
        "nonresrepo",
        1,
        "stock",
        1,
        6,
        null,
        null,
        "2022-06-27",
        "2026-02-07",
        0,
        "EUR",
        "%"
      ],
      [
        "RU000A0ZZ885",
        "CPEY",
        "REPO-M: Non-residents (CNY) - negotiated",
        1077,
        1017,
        "nonresrepo",
        1,
        "stock",
        1,
        6,
        null,
        null,
        "2022-09-26",
        "2026-02-07",
        0,
        "CNY",
        "%"
      ],
      [
        "RU000A0ZZ885",
        "OBBO",
        "OffBoard bonds",
        141,
        39,
        "bonds",
        7,
        "offboard",
        0,
        2,
        "2018-11-08",
        "2020-02-10",
        "2018-11-08",
        "2022-12-30",
        0,
        null,
        "%"
      ],
      [
        "RU000A0ZZ885",
        "QBND",
        "Quotes",
        1280,
        1279,
        "bonds",
        1282,
        "quotes",
        1,
        4,
        null,
        null,
        "2023-06-05",
        "2026-02-06",
        0,
        null,
        "%"
      ]
    ]
  }
}